{
  "subject": "الرياضيات",
  "description": "مكتبة الرياضيات الشاملة لطلاب الثانوية والجامعات",
  "lessons": [
    {
      "id": 1,
      "title": "المعادلات الخطية",
      "content": "المعادلة الخطية هي معادلة من الدرجة الأولى تكون على الصورة: ax + b = 0، حيث a و b أعداد حقيقية و a ≠ 0.\n\nطريقة الحل:\n1. نقل الحد الثابت إلى الطرف الآخر: ax = -b\n2. قسمة الطرفين على a: x = -b/a\n\nمثال:\nحل المعادلة: 3x + 6 = 0\n3x = -6\nx = -6/3\nx = -2",
      "formulas": ["ax + b = 0", "x = -b/a"],
      "examples": [
        {
          "problem": "حل المعادلة: 2x + 8 = 0",
          "solution": "2x = -8\nx = -8/2\nx = -4"
        },
        {
          "problem": "حل المعادلة: 5x - 15 = 0",
          "solution": "5x = 15\nx = 15/5\nx = 3"
        }
      ]
    },
    {
      "id": 2,
      "title": "المعادلات التربيعية",
      "content": "المعادلة التربيعية هي معادلة من الدرجة الثانية على الصورة: ax² + bx + c = 0، حيث a ≠ 0.\n\nطريقة الحل باستخدام المميز:\n1. حساب المميز: Δ = b² - 4ac\n2. إذا كان Δ > 0: يوجد حلان حقيقيان مختلفان\n3. إذا كان Δ = 0: يوجد حل واحد مكرر\n4. إذا كان Δ < 0: لا يوجد حلول حقيقية (حلول مركبة)\n\nالصيغة العامة: x = [-b ± √Δ] / 2a",
      "formulas": ["ax² + bx + c = 0", "Δ = b² - 4ac", "x = [-b ± √Δ] / 2a"],
      "examples": [
        {
          "problem": "حل المعادلة: x² - 5x + 6 = 0",
          "solution": "Δ = 25 - 24 = 1\nx = [5 ± 1] / 2\nx₁ = 3, x₂ = 2"
        }
      ]
    },
    {
      "id": 3,
      "title": "نظرية فيثاغورس",
      "content": "في المثلث القائم الزاوية، مربع طول الوتر يساوي مجموع مربعي طولي الضلعين الآخرين.\n\nالصيغة: a² + b² = c²\nحيث:\n- c هو طول الوتر (الضلع المقابل للزاوية القائمة)\n- a و b هما طولا الضلعين الآخرين",
      "formulas": ["a² + b² = c²"],
      "examples": [
        {
          "problem": "إذا كان طولا ضلعي المثلث القائم 3 و 4، فما طول الوتر؟",
          "solution": "c² = 3² + 4² = 9 + 16 = 25\nc = √25 = 5"
        }
      ]
    }
  ]
}
